{
  "type": "FeatureCollection",
  "features": [
    {
      "type": "Feature",
      "geometry": {
        "type": "Point",
        "coordinates": [-26.191222, 28.038583]
      },
      "properties": {
        "name": "Joburg Theatre"
      }
    }
  ]
}
